{"v":"4.8.0","meta":{"g":"LottieFiles AE 3.5.7","a":"","k":"","d":"","tc":""},"fr":29.9700012207031,"ip":0,"op":150.000006109625,"w":360,"h":288,"nm":"STEP2","ddd":0,"assets":[],"layers":[{"ddd":0,"ind":1,"ty":4,"nm":"Layer 18","sr":1,"ks":{"o":{"a":0,"k":100,"ix":11},"r":{"a":1,"k":[{"i":{"x":[0.667],"y":[1]},"o":{"x":[0.333],"y":[0]},"t":0,"s":[-46]},{"t":14.0000005702317,"s":[0]}],"ix":10},"p":{"a":1,"k":[{"i":{"x":0.667,"y":0.519},"o":{"x":0.333,"y":0},"t":0,"s":[210.759,153.634,0],"to":[0,0,0],"ti":[0,0,0]},{"i":{"x":0.667,"y":1},"o":{"x":0.088,"y":1},"t":13,"s":[299.353,170.509,0],"to":[0,0,0],"ti":[0,0,0]},{"t":32.0000013033867,"s":[315.759,173.634,0]}],"ix":2},"a":{"a":0,"k":[315.759,173.634,0],"ix":1},"s":{"a":1,"k":[{"i":{"x":[0.667,0.667,0.667],"y":[1,1,1]},"o":{"x":[0.333,0.333,0.333],"y":[0,0,0]},"t":0,"s":[30,30,100]},{"t":12.00000048877,"s":[100,100,100]}],"ix":6}},"ao":0,"shapes":[{"ty":"gr","it":[{"ty":"gr","it":[{"ind":0,"ty":"sh","ix":1,"ks":{"a":0,"k":{"i":[[-0.166,0.071],[-0.062,0.155],[0.071,0.166],[0.155,0.062],[0.166,-0.071],[0.062,-0.155],[-0.071,-0.166],[-0.155,-0.062]],"o":[[0.166,-0.071],[0.063,-0.155],[-0.071,-0.166],[-0.155,-0.062],[-0.166,0.071],[-0.062,0.155],[0.071,0.166],[0.155,0.063]],"v":[[-1.032,-2.417],[-0.689,-2.757],[-0.702,-3.238],[-1.041,-3.582],[-1.524,-3.568],[-1.866,-3.229],[-1.853,-2.747],[-1.514,-2.405]],"c":true},"ix":2},"nm":"Path 1","mn":"ADBE Vector Shape - Group","hd":false},{"ind":1,"ty":"sh","ix":2,"ks":{"a":0,"k":{"i":[[-0.166,0.071],[-0.062,0.155],[0.071,0.166],[0.155,0.062],[0.166,-0.071],[0.062,-0.155],[-0.071,-0.166],[-0.155,-0.062]],"o":[[0.166,-0.071],[0.063,-0.155],[-0.071,-0.166],[-0.155,-0.062],[-0.166,0.071],[-0.062,0.155],[0.071,0.166],[0.155,0.063]],"v":[[0.246,0.576],[0.589,0.236],[0.576,-0.246],[0.236,-0.589],[-0.246,-0.576],[-0.588,-0.237],[-0.576,0.246],[-0.236,0.588]],"c":true},"ix":2},"nm":"Path 2","mn":"ADBE Vector Shape - Group","hd":false},{"ind":2,"ty":"sh","ix":3,"ks":{"a":0,"k":{"i":[[-0.166,0.071],[-0.062,0.155],[0.071,0.166],[0.155,0.062],[0.166,-0.071],[0.062,-0.155],[-0.071,-0.166],[-0.155,-0.062]],"o":[[0.166,-0.071],[0.062,-0.155],[-0.071,-0.166],[-0.155,-0.062],[-0.166,0.071],[-0.063,0.155],[0.071,0.166],[0.155,0.063]],"v":[[1.524,3.568],[1.867,3.229],[1.853,2.747],[1.515,2.404],[1.032,2.417],[0.69,2.757],[0.702,3.238],[1.042,3.581]],"c":true},"ix":2},"nm":"Path 3","mn":"ADBE Vector Shape - Group","hd":false},{"ind":3,"ty":"sh","ix":4,"ks":{"a":0,"k":{"i":[[0,0],[0,0],[0,0],[0.474,0.349],[0.235,0.55],[-0.076,0.585],[-0.353,0.484],[0,0],[0,0],[0,0],[-0.474,-0.349],[-0.235,-0.55],[0.075,-0.585],[0.353,-0.484]],"o":[[0,0],[0,0],[-0.594,-0.079],[-0.475,-0.35],[-0.235,-0.55],[0.076,-0.584],[0,0],[0,0],[0,0],[0.594,0.079],[0.474,0.35],[0.235,0.55],[-0.076,0.584],[0,0]],"v":[[-4.173,7.226],[8.105,1.983],[7.27,0.026],[5.668,-0.616],[4.604,-1.966],[4.365,-3.668],[5.009,-5.269],[4.173,-7.226],[-8.105,-1.983],[-7.27,-0.026],[-5.668,0.616],[-4.604,1.966],[-4.365,3.668],[-5.009,5.269]],"c":true},"ix":2},"nm":"Path 4","mn":"ADBE Vector Shape - Group","hd":false},{"ind":4,"ty":"sh","ix":5,"ks":{"a":0,"k":{"i":[[0,0],[0.319,0.128],[0.137,0.32],[0,0],[-0.147,0.471],[0.197,0.46],[0.442,0.22],[0.468,-0.109],[0,0],[-0.129,0.319],[-0.319,0.136],[0,0],[-0.319,-0.128],[-0.137,-0.32],[0,0],[0.147,-0.471],[-0.197,-0.46],[-0.442,-0.22],[-0.468,0.109],[0,0],[0.129,-0.319],[0.319,-0.136]],"o":[[-0.319,0.136],[-0.319,-0.128],[0,0],[0.402,-0.262],[0.147,-0.471],[-0.197,-0.46],[-0.442,-0.22],[0,0],[-0.137,-0.32],[0.128,-0.319],[0,0],[0.319,-0.136],[0.319,0.128],[0,0],[-0.402,0.262],[-0.147,0.471],[0.197,0.46],[0.442,0.22],[0,0],[0.137,0.32],[-0.128,0.319],[0,0]],"v":[[-3.682,8.377],[-4.64,8.389],[-5.324,7.717],[-6.504,4.955],[-5.681,3.855],[-5.755,2.458],[-6.713,1.437],[-8.077,1.271],[-9.256,-1.491],[-9.268,-2.45],[-8.597,-3.134],[3.682,-8.377],[4.64,-8.389],[5.324,-7.717],[6.504,-4.955],[5.681,-3.855],[5.755,-2.458],[6.713,-1.437],[8.077,-1.271],[9.256,1.491],[9.268,2.45],[8.597,3.134]],"c":true},"ix":2},"nm":"Path 5","mn":"ADBE Vector Shape - Group","hd":false},{"ty":"fl","c":{"a":0,"k":[1,0.807843148708,0,1],"ix":4},"o":{"a":0,"k":100,"ix":5},"r":1,"bm":0,"nm":"Fill 1","mn":"ADBE Vector Graphic - Fill","hd":false},{"ty":"tr","p":{"a":0,"k":[0,0],"ix":2},"a":{"a":0,"k":[0,0],"ix":1},"s":{"a":0,"k":[100,100],"ix":3},"r":{"a":0,"k":0,"ix":6},"o":{"a":0,"k":100,"ix":7},"sk":{"a":0,"k":0,"ix":4},"sa":{"a":0,"k":0,"ix":5},"nm":"Transform"}],"nm":"Group 1","np":6,"cix":2,"bm":0,"ix":1,"mn":"ADBE Vector Group","hd":false},{"ty":"tr","p":{"a":0,"k":[315.759,173.634],"ix":2},"a":{"a":0,"k":[0,0],"ix":1},"s":{"a":0,"k":[100,100],"ix":3},"r":{"a":0,"k":0,"ix":6},"o":{"a":0,"k":100,"ix":7},"sk":{"a":0,"k":0,"ix":4},"sa":{"a":0,"k":0,"ix":5},"nm":"Transform"}],"nm":"Group 1","np":1,"cix":2,"bm":0,"ix":1,"mn":"ADBE Vector Group","hd":false}],"ip":4.00000016292334,"op":150.000006109625,"st":0,"bm":0},{"ddd":0,"ind":2,"ty":4,"nm":"Layer 16","sr":1,"ks":{"o":{"a":0,"k":100,"ix":11},"r":{"a":1,"k":[{"i":{"x":[0.667],"y":[1]},"o":{"x":[0.333],"y":[0]},"t":0,"s":[40]},{"t":15.0000006109625,"s":[0]}],"ix":10},"p":{"a":1,"k":[{"i":{"x":0.667,"y":0.444},"o":{"x":0.333,"y":0},"t":0,"s":[132.956,148.095,0],"to":[0,0,0],"ti":[0,0,0]},{"i":{"x":0.667,"y":1},"o":{"x":0.098,"y":1},"t":15,"s":[57.019,169.189,0],"to":[0,0,0],"ti":[0,0,0]},{"t":32.0000013033867,"s":[42.956,173.095,0]}],"ix":2},"a":{"a":0,"k":[0,0,0],"ix":1},"s":{"a":1,"k":[{"i":{"x":[0.667,0.667,0.667],"y":[1,1,1]},"o":{"x":[0.333,0.333,0.333],"y":[0,0,0]},"t":0,"s":[30,30,100]},{"t":12.00000048877,"s":[100,100,100]}],"ix":6}},"ao":0,"shapes":[{"ty":"gr","it":[{"ind":0,"ty":"sh","ix":1,"ks":{"a":0,"k":{"i":[[-0.24,-0.072],[-0.204,0.11],[-0.072,0.24],[0.109,0.204],[0.24,0.072],[0.204,-0.11],[0.072,-0.24],[-0.11,-0.203]],"o":[[0.24,0.072],[0.203,-0.109],[0.072,-0.24],[-0.11,-0.204],[-0.24,-0.072],[-0.204,0.11],[-0.072,0.24],[0.11,0.204]],"v":[[1.047,-3.49],[1.714,-3.547],[2.127,-4.072],[2.071,-4.738],[1.545,-5.152],[0.88,-5.095],[0.465,-4.57],[0.523,-3.905]],"c":true},"ix":2},"nm":"Path 1","mn":"ADBE Vector Shape - Group","hd":false},{"ind":1,"ty":"sh","ix":2,"ks":{"a":0,"k":{"i":[[-0.24,-0.072],[-0.204,0.11],[-0.072,0.24],[0.109,0.204],[0.24,0.072],[0.204,-0.11],[0.072,-0.24],[-0.11,-0.203]],"o":[[0.24,0.072],[0.203,-0.109],[0.072,-0.24],[-0.11,-0.204],[-0.24,-0.072],[-0.204,0.11],[-0.072,0.24],[0.11,0.204]],"v":[[-0.249,0.831],[0.418,0.774],[0.831,0.249],[0.775,-0.417],[0.249,-0.831],[-0.416,-0.774],[-0.831,-0.249],[-0.773,0.417]],"c":true},"ix":2},"nm":"Path 2","mn":"ADBE Vector Shape - Group","hd":false},{"ind":2,"ty":"sh","ix":3,"ks":{"a":0,"k":{"i":[[-0.24,-0.072],[-0.204,0.11],[-0.072,0.24],[0.11,0.203],[0.24,0.072],[0.204,-0.11],[0.072,-0.24],[-0.11,-0.204]],"o":[[0.24,0.072],[0.204,-0.11],[0.072,-0.24],[-0.11,-0.204],[-0.24,-0.072],[-0.204,0.109],[-0.072,0.24],[0.11,0.204]],"v":[[-1.546,5.152],[-0.879,5.096],[-0.465,4.57],[-0.522,3.905],[-1.047,3.49],[-1.713,3.548],[-2.127,4.072],[-2.07,4.738]],"c":true},"ix":2},"nm":"Path 3","mn":"ADBE Vector Shape - Group","hd":false},{"ind":3,"ty":"sh","ix":4,"ks":{"a":0,"k":{"i":[[0,0],[0,0],[0,0],[0.195,0.792],[-0.238,0.794],[-0.6,0.556],[-0.805,0.201],[0,0],[0,0],[0,0],[-0.195,-0.792],[0.238,-0.794],[0.599,-0.556],[0.805,-0.201]],"o":[[0,0],[0,0],[-0.561,-0.611],[-0.195,-0.794],[0.238,-0.794],[0.599,-0.554],[0,0],[0,0],[0,0],[0.561,0.611],[0.194,0.794],[-0.238,0.794],[-0.599,0.554],[0,0]],"v":[[-10.858,3.989],[6.87,9.307],[7.717,6.481],[6.583,4.376],[6.648,1.994],[7.905,-0.03],[10.01,-1.164],[10.858,-3.989],[-6.87,-9.307],[-7.717,-6.481],[-6.582,-4.376],[-6.648,-1.994],[-7.904,0.03],[-10.01,1.164]],"c":true},"ix":2},"nm":"Path 4","mn":"ADBE Vector Shape - Group","hd":false},{"ind":4,"ty":"sh","ix":5,"ks":{"a":0,"k":{"i":[[0,0],[0.226,0.42],[-0.139,0.462],[0,0],[-0.574,0.371],[-0.199,0.665],[0.275,0.626],[0.595,0.299],[0,0],[-0.42,0.225],[-0.462,-0.138],[0,0],[-0.226,-0.42],[0.139,-0.462],[0,0],[0.574,-0.371],[0.199,-0.665],[-0.275,-0.626],[-0.595,-0.299],[0,0],[0.42,-0.225],[0.462,0.138]],"o":[[-0.462,-0.138],[-0.227,-0.419],[0,0],[0.661,0.078],[0.574,-0.371],[0.199,-0.665],[-0.275,-0.626],[0,0],[0.139,-0.462],[0.42,-0.226],[0,0],[0.462,0.138],[0.227,0.419],[0,0],[-0.661,-0.078],[-0.574,0.371],[-0.199,0.665],[0.275,0.626],[0,0],[-0.139,0.462],[-0.42,0.226],[0,0]],"v":[[-11.357,5.651],[-12.388,4.813],[-12.52,3.49],[-11.323,-0.498],[-9.47,-0.939],[-8.31,-2.493],[-8.423,-4.429],[-9.728,-5.817],[-8.532,-9.805],[-7.693,-10.836],[-6.371,-10.969],[11.357,-5.651],[12.388,-4.813],[12.52,-3.49],[11.323,0.498],[9.47,0.939],[8.31,2.493],[8.423,4.429],[9.728,5.817],[8.532,9.805],[7.693,10.836],[6.371,10.969]],"c":true},"ix":2},"nm":"Path 5","mn":"ADBE Vector Shape - Group","hd":false},{"ty":"fl","c":{"a":0,"k":[0.949019610882,0.662745118141,0.764705896378,1],"ix":4},"o":{"a":0,"k":100,"ix":5},"r":1,"bm":0,"nm":"Fill 1","mn":"ADBE Vector Graphic - Fill","hd":false},{"ty":"tr","p":{"a":0,"k":[0,0],"ix":2},"a":{"a":0,"k":[0,0],"ix":1},"s":{"a":0,"k":[100,100],"ix":3},"r":{"a":0,"k":0,"ix":6},"o":{"a":0,"k":100,"ix":7},"sk":{"a":0,"k":0,"ix":4},"sa":{"a":0,"k":0,"ix":5},"nm":"Transform"}],"nm":"Group 1","np":6,"cix":2,"bm":0,"ix":1,"mn":"ADBE Vector Group","hd":false}],"ip":4.00000016292334,"op":150.000006109625,"st":0,"bm":0},{"ddd":0,"ind":3,"ty":4,"nm":"Layer 12","sr":1,"ks":{"o":{"a":0,"k":100,"ix":11},"r":{"a":1,"k":[{"i":{"x":[0.667],"y":[1]},"o":{"x":[0.333],"y":[0]},"t":0,"s":[21]},{"t":16.0000006516934,"s":[0]}],"ix":10},"p":{"a":1,"k":[{"i":{"x":0.667,"y":0.444},"o":{"x":0.333,"y":0},"t":0,"s":[122.626,138.427,0],"to":[0,0,0],"ti":[0,0,0]},{"i":{"x":0.667,"y":1},"o":{"x":0.093,"y":1},"t":15,"s":[72.001,87.802,0],"to":[0,0,0],"ti":[0,0,0]},{"t":33.0000013441176,"s":[62.626,78.427,0]}],"ix":2},"a":{"a":0,"k":[0,0,0],"ix":1},"s":{"a":1,"k":[{"i":{"x":[0.667,0.667,0.667],"y":[1,1,1]},"o":{"x":[0.333,0.333,0.333],"y":[0,0,0]},"t":0,"s":[30,30,100]},{"t":12.00000048877,"s":[100,100,100]}],"ix":6}},"ao":0,"shapes":[{"ty":"gr","it":[{"ind":0,"ty":"sh","ix":1,"ks":{"a":0,"k":{"i":[[0,0],[0,0],[0,0],[0,0],[0,0],[0,0],[0,0],[0,0]],"o":[[0,0],[0,0],[0,0],[0,0],[0,0],[0,0],[0,0],[0,0]],"v":[[-3.376,12.816],[-7.881,6.805],[-15.248,5.27],[-9.246,0.729],[-7.746,-6.631],[-3.205,-0.629],[4.162,0.908],[-1.84,5.448]],"c":true},"ix":2},"nm":"Path 1","mn":"ADBE Vector Shape - Group","hd":false},{"ind":1,"ty":"sh","ix":2,"ks":{"a":0,"k":{"i":[[0,0],[0,0],[0,0],[0,0],[0,0],[0,0],[0,0],[0,0]],"o":[[0,0],[0,0],[0,0],[0,0],[0,0],[0,0],[0,0],[0,0]],"v":[[11.479,14.585],[9.23,11.597],[5.525,10.816],[8.548,8.559],[9.294,4.862],[11.55,7.884],[15.248,8.631],[12.233,10.923]],"c":true},"ix":2},"nm":"Path 2","mn":"ADBE Vector Shape - Group","hd":false},{"ind":2,"ty":"sh","ix":3,"ks":{"a":0,"k":{"i":[[0,0],[0,0],[0,0],[0,0],[0,0],[0,0],[0,0],[0,0]],"o":[[0,0],[0,0],[0,0],[0,0],[0,0],[0,0],[0,0],[0,0]],"v":[[7.109,-4.862],[4.852,-7.885],[1.155,-8.631],[4.17,-10.923],[4.924,-14.585],[7.172,-11.597],[10.878,-10.816],[7.855,-8.56]],"c":true},"ix":2},"nm":"Path 3","mn":"ADBE Vector Shape - Group","hd":false},{"ty":"fl","c":{"a":0,"k":[0.549019634724,0.878431379795,0.745098054409,1],"ix":4},"o":{"a":0,"k":100,"ix":5},"r":1,"bm":0,"nm":"Fill 1","mn":"ADBE Vector Graphic - Fill","hd":false},{"ty":"tr","p":{"a":0,"k":[0,0],"ix":2},"a":{"a":0,"k":[0,0],"ix":1},"s":{"a":0,"k":[100,100],"ix":3},"r":{"a":0,"k":0,"ix":6},"o":{"a":0,"k":100,"ix":7},"sk":{"a":0,"k":0,"ix":4},"sa":{"a":0,"k":0,"ix":5},"nm":"Transform"}],"nm":"Group 1","np":4,"cix":2,"bm":0,"ix":1,"mn":"ADBE Vector Group","hd":false}],"ip":4.00000016292334,"op":150.000006109625,"st":0,"bm":0},{"ddd":0,"ind":4,"ty":4,"nm":"Layer 11","sr":1,"ks":{"o":{"a":0,"k":100,"ix":11},"r":{"a":1,"k":[{"i":{"x":[0.667],"y":[1]},"o":{"x":[0.333],"y":[0]},"t":0,"s":[60]},{"t":18.000000733155,"s":[0]}],"ix":10},"p":{"a":1,"k":[{"i":{"x":0.667,"y":0.259},"o":{"x":0.333,"y":0},"t":0,"s":[235.2,138.238,0],"to":[0,0,0],"ti":[0,0,0]},{"i":{"x":0.667,"y":1},"o":{"x":0.093,"y":1},"t":20,"s":[306.918,100.269,0],"to":[0,0,0],"ti":[0,0,0]},{"t":38.0000015477717,"s":[320.2,93.238,0]}],"ix":2},"a":{"a":0,"k":[0,0,0],"ix":1},"s":{"a":1,"k":[{"i":{"x":[0.667,0.667,0.667],"y":[1,1,1]},"o":{"x":[0.333,0.333,0.333],"y":[0,0,0]},"t":0,"s":[30,30,100]},{"t":12.00000048877,"s":[100,100,100]}],"ix":6}},"ao":0,"shapes":[{"ty":"gr","it":[{"ind":0,"ty":"sh","ix":1,"ks":{"a":0,"k":{"i":[[0.273,-0.073],[0.226,0.13],[0.073,0.273],[0,0],[-0.128,0.237],[-0.274,0.073],[-0.23,-0.141],[-0.067,-0.252],[0,0],[0.13,-0.227]],"o":[[-0.274,0.073],[-0.227,-0.131],[0,0],[-0.067,-0.252],[0.127,-0.237],[0.273,-0.073],[0.229,0.142],[0,0],[0.073,0.273],[-0.131,0.226]],"v":[[3.502,13.084],[2.753,12.998],[2.302,12.392],[0.952,7.347],[1.044,6.613],[1.645,6.148],[2.4,6.25],[2.844,6.841],[4.194,11.886],[4.108,12.635]],"c":true},"ix":2},"nm":"Path 1","mn":"ADBE Vector Shape - Group","hd":false},{"ind":1,"ty":"sh","ix":2,"ks":{"a":0,"k":{"i":[[0.26,0.133],[0.07,0.262],[-0.123,0.214],[0,0],[-0.252,0.067],[-0.24,-0.139],[-0.068,-0.253],[0.139,-0.24],[0,0],[0.242,-0.065]],"o":[[-0.219,-0.144],[-0.07,-0.262],[0,0],[0.123,-0.213],[0.252,-0.067],[0.24,0.139],[0.067,0.252],[0,0],[-0.123,0.214],[-0.242,0.065]],"v":[[-5.01,8.673],[-5.443,8.062],[-5.364,7.348],[-4.51,5.87],[-3.947,5.449],[-3.209,5.556],[-2.748,6.142],[-2.855,6.88],[-3.709,8.358],[-4.256,8.775]],"c":true},"ix":2},"nm":"Path 2","mn":"ADBE Vector Shape - Group","hd":false},{"ind":2,"ty":"sh","ix":3,"ks":{"a":0,"k":{"i":[[0.213,0.123],[0,0],[0.067,0.252],[-0.139,0.24],[-0.252,0.067],[-0.24,-0.139],[0,0],[-0.065,-0.243],[0.133,-0.261],[0.263,-0.07]],"o":[[0,0],[-0.214,-0.123],[-0.068,-0.253],[0.139,-0.24],[0.253,-0.068],[0,0],[0.213,0.123],[0.064,0.241],[-0.144,0.218],[-0.262,0.07]],"v":[[7.348,5.366],[5.869,4.512],[5.449,3.949],[5.555,3.21],[6.141,2.75],[6.879,2.856],[8.357,3.71],[8.774,4.258],[8.672,5.011],[8.061,5.445]],"c":true},"ix":2},"nm":"Path 3","mn":"ADBE Vector Shape - Group","hd":false},{"ind":3,"ty":"sh","ix":4,"ks":{"a":0,"k":{"i":[[0.882,-0.236],[0.773,0.447],[0.236,0.882],[-0.446,0.773],[-0.883,0.236],[-0.773,-0.446],[-0.236,-0.882],[0.447,-0.772]],"o":[[-0.883,0.236],[-0.772,-0.446],[-0.236,-0.882],[0.447,-0.772],[0.882,-0.236],[0.773,0.447],[0.236,0.882],[-0.447,0.773]],"v":[[0.844,3.153],[-1.64,2.838],[-3.153,0.845],[-2.838,-1.639],[-0.843,-3.151],[1.639,-2.837],[3.152,-0.843],[2.837,1.64]],"c":true},"ix":2},"nm":"Path 4","mn":"ADBE Vector Shape - Group","hd":false},{"ind":4,"ty":"sh","ix":5,"ks":{"a":0,"k":{"i":[[0,0],[0.237,0.128],[0.073,0.274],[-0.141,0.23],[-0.252,0.067],[0,0],[-0.227,-0.131],[-0.073,-0.274],[0.13,-0.226],[0.274,-0.073]],"o":[[-0.252,0.067],[-0.237,-0.127],[-0.073,-0.274],[0.141,-0.23],[0,0],[0.274,-0.073],[0.226,0.131],[0.073,0.274],[-0.131,0.227],[0,0]],"v":[[7.347,-0.951],[6.612,-1.043],[6.147,-1.644],[6.25,-2.398],[6.84,-2.843],[11.884,-4.193],[12.635,-4.107],[13.083,-3.5],[12.997,-2.751],[12.39,-2.301]],"c":true},"ix":2},"nm":"Path 5","mn":"ADBE Vector Shape - Group","hd":false},{"ind":5,"ty":"sh","ix":6,"ks":{"a":0,"k":{"i":[[0.24,0.139],[0.068,0.253],[-0.139,0.239],[0,0],[-0.243,0.065],[-0.261,-0.133],[-0.07,-0.263],[0.123,-0.213],[0,0],[0.253,-0.068]],"o":[[-0.24,-0.139],[-0.067,-0.252],[0,0],[0.123,-0.213],[0.241,-0.064],[0.218,0.144],[0.07,0.262],[0,0],[-0.123,0.213],[-0.252,0.067]],"v":[[3.21,-5.554],[2.749,-6.14],[2.855,-6.878],[3.709,-8.357],[4.257,-8.773],[5.011,-8.671],[5.444,-8.06],[5.365,-7.347],[4.51,-5.868],[3.947,-5.447]],"c":true},"ix":2},"nm":"Path 6","mn":"ADBE Vector Shape - Group","hd":false},{"ind":6,"ty":"sh","ix":7,"ks":{"a":0,"k":{"i":[[0.273,-0.073],[0.226,0.131],[0.068,0.253],[0,0],[-0.134,0.216],[-0.274,0.073],[-0.224,-0.121],[-0.073,-0.274],[0,0],[0.13,-0.227]],"o":[[-0.274,0.073],[-0.227,-0.131],[0,0],[-0.073,-0.274],[0.133,-0.216],[0.273,-0.073],[0.223,0.12],[0,0],[0.068,0.253],[-0.131,0.227]],"v":[[-1.645,-6.147],[-2.394,-6.234],[-2.836,-6.808],[-4.202,-11.914],[-4.111,-12.648],[-3.501,-13.082],[-2.755,-13.011],[-2.311,-12.42],[-0.945,-7.314],[-1.038,-6.596]],"c":true},"ix":2},"nm":"Path 7","mn":"ADBE Vector Shape - Group","hd":false},{"ind":7,"ty":"sh","ix":8,"ks":{"a":0,"k":{"i":[[0.24,0.139],[0,0],[0.065,0.242],[-0.133,0.26],[-0.263,0.07],[-0.213,-0.123],[0,0],[-0.067,-0.252],[0.139,-0.24],[0.252,-0.067]],"o":[[0,0],[-0.213,-0.124],[-0.065,-0.242],[0.144,-0.218],[0.262,-0.07],[0,0],[0.214,0.123],[0.068,0.253],[-0.139,0.24],[-0.252,0.067]],"v":[[-6.879,-2.854],[-8.358,-3.708],[-8.774,-4.256],[-8.672,-5.009],[-8.061,-5.443],[-7.348,-5.363],[-5.87,-4.509],[-5.448,-3.947],[-5.555,-3.208],[-6.141,-2.747]],"c":true},"ix":2},"nm":"Path 8","mn":"ADBE Vector Shape - Group","hd":false},{"ind":8,"ty":"sh","ix":9,"ks":{"a":0,"k":{"i":[[0,0],[0.226,0.131],[0.073,0.274],[-0.131,0.227],[-0.274,0.073],[0,0],[-0.237,-0.128],[-0.073,-0.274],[0.142,-0.229],[0.252,-0.067]],"o":[[-0.274,0.073],[-0.227,-0.13],[-0.073,-0.274],[0.13,-0.227],[0,0],[0.252,-0.067],[0.237,0.128],[0.073,0.274],[-0.141,0.23],[0,0]],"v":[[-11.884,4.195],[-12.633,4.108],[-13.083,3.503],[-12.996,2.752],[-12.39,2.303],[-7.346,0.953],[-6.613,1.044],[-6.148,1.646],[-6.25,2.4],[-6.84,2.845]],"c":true},"ix":2},"nm":"Path 9","mn":"ADBE Vector Shape - Group","hd":false},{"ty":"fl","c":{"a":0,"k":[0.549019634724,0.878431379795,0.745098054409,1],"ix":4},"o":{"a":0,"k":100,"ix":5},"r":1,"bm":0,"nm":"Fill 1","mn":"ADBE Vector Graphic - Fill","hd":false},{"ty":"tr","p":{"a":0,"k":[0,0],"ix":2},"a":{"a":0,"k":[0,0],"ix":1},"s":{"a":0,"k":[100,100],"ix":3},"r":{"a":0,"k":0,"ix":6},"o":{"a":0,"k":100,"ix":7},"sk":{"a":0,"k":0,"ix":4},"sa":{"a":0,"k":0,"ix":5},"nm":"Transform"}],"nm":"Group 1","np":10,"cix":2,"bm":0,"ix":1,"mn":"ADBE Vector Group","hd":false}],"ip":4.00000016292334,"op":150.000006109625,"st":0,"bm":0},{"ddd":0,"ind":5,"ty":4,"nm":"Layer 8","sr":1,"ks":{"o":{"a":0,"k":100,"ix":11},"r":{"a":1,"k":[{"i":{"x":[0.667],"y":[1]},"o":{"x":[0.333],"y":[0]},"t":0,"s":[-19]},{"t":16.0000006516934,"s":[0]}],"ix":10},"p":{"a":1,"k":[{"i":{"x":0.667,"y":0.236},"o":{"x":0.333,"y":0},"t":0,"s":[248.879,164.182,0],"to":[0,0,0],"ti":[0,0,0]},{"i":{"x":0.667,"y":1},"o":{"x":0.111,"y":1},"t":17,"s":[294.504,216.682,0],"to":[0,0,0],"ti":[0,0,0]},{"t":32.0000013033867,"s":[303.879,229.182,0]}],"ix":2},"a":{"a":0,"k":[0,0,0],"ix":1},"s":{"a":1,"k":[{"i":{"x":[0.667,0.667,0.667],"y":[1,1,1]},"o":{"x":[0.333,0.333,0.333],"y":[0,0,0]},"t":0,"s":[30,30,100]},{"t":12.00000048877,"s":[100,100,100]}],"ix":6}},"ao":0,"shapes":[{"ty":"gr","it":[{"ind":0,"ty":"sh","ix":1,"ks":{"a":0,"k":{"i":[[0,0],[0,0],[0,0],[0,0],[0,0],[0,0],[0,0],[0,0]],"o":[[0,0],[0,0],[0,0],[0,0],[0,0],[0,0],[0,0],[0,0]],"v":[[-3.767,11.999],[-7.853,5.698],[-15.099,3.665],[-8.803,-0.458],[-6.805,-7.698],[-2.683,-1.402],[4.563,0.632],[-1.733,4.753]],"c":true},"ix":2},"nm":"Path 1","mn":"ADBE Vector Shape - Group","hd":false},{"ind":1,"ty":"sh","ix":2,"ks":{"a":0,"k":{"i":[[0,0],[0,0],[0,0],[0,0],[0,0],[0,0],[0,0],[0,0]],"o":[[0,0],[0,0],[0,0],[0,0],[0,0],[0,0],[0,0],[0,0]],"v":[[10.934,14.773],[8.894,11.64],[5.249,10.608],[8.419,8.563],[9.414,4.924],[11.46,8.094],[15.099,9.089],[11.935,11.171]],"c":true},"ix":2},"nm":"Path 2","mn":"ADBE Vector Shape - Group","hd":false},{"ind":2,"ty":"sh","ix":3,"ks":{"a":0,"k":{"i":[[0,0],[0,0],[0,0],[0,0],[0,0],[0,0],[0,0],[0,0]],"o":[[0,0],[0,0],[0,0],[0,0],[0,0],[0,0],[0,0],[0,0]],"v":[[7.895,-4.924],[5.85,-8.094],[2.211,-9.089],[5.375,-11.171],[6.376,-14.773],[8.416,-11.64],[12.06,-10.608],[8.89,-8.563]],"c":true},"ix":2},"nm":"Path 3","mn":"ADBE Vector Shape - Group","hd":false},{"ty":"fl","c":{"a":0,"k":[0.949019610882,0.662745118141,0.764705896378,1],"ix":4},"o":{"a":0,"k":100,"ix":5},"r":1,"bm":0,"nm":"Fill 1","mn":"ADBE Vector Graphic - Fill","hd":false},{"ty":"tr","p":{"a":0,"k":[0,0],"ix":2},"a":{"a":0,"k":[0,0],"ix":1},"s":{"a":0,"k":[100,100],"ix":3},"r":{"a":0,"k":0,"ix":6},"o":{"a":0,"k":100,"ix":7},"sk":{"a":0,"k":0,"ix":4},"sa":{"a":0,"k":0,"ix":5},"nm":"Transform"}],"nm":"Group 1","np":4,"cix":2,"bm":0,"ix":1,"mn":"ADBE Vector Group","hd":false}],"ip":4.00000016292334,"op":150.000006109625,"st":0,"bm":0},{"ddd":0,"ind":6,"ty":4,"nm":"Layer 4","sr":1,"ks":{"o":{"a":0,"k":100,"ix":11},"r":{"a":1,"k":[{"i":{"x":[0.188],"y":[0.985]},"o":{"x":[0.04],"y":[0.001]},"t":0,"s":[-27]},{"t":47.0000019143492,"s":[-387]}],"ix":10},"p":{"a":1,"k":[{"i":{"x":0.667,"y":0.335},"o":{"x":0.333,"y":0},"t":0,"s":[148.879,148.079,0],"to":[0,0,0],"ti":[0,0,0]},{"i":{"x":0.667,"y":1},"o":{"x":0.184,"y":1},"t":18,"s":[179.379,226.954,0],"to":[0,0,0],"ti":[0,0,0]},{"t":34.0000013848484,"s":[188.379,253.079,0]}],"ix":2},"a":{"a":0,"k":[0,0,0],"ix":1},"s":{"a":1,"k":[{"i":{"x":[0.667,0.667,0.667],"y":[1,1,1]},"o":{"x":[0.333,0.333,0.333],"y":[0,0,0]},"t":0,"s":[30,30,100]},{"t":12.00000048877,"s":[100,100,100]}],"ix":6}},"ao":0,"shapes":[{"ty":"gr","it":[{"ind":0,"ty":"sh","ix":1,"ks":{"a":0,"k":{"i":[[0,0],[0,0],[-0.939,0.317],[0,0],[0.14,0.428],[0,0],[0.423,-0.143],[0,0],[-0.582,0.825],[0,0],[0.36,0.27],[0,0],[0.262,-0.365],[0,0],[0.036,0.967],[0,0],[0.446,0],[0,0],[0,-0.46],[0,0],[0.573,0.809],[0,0],[0.362,-0.27],[0,0],[-0.262,-0.381],[0,0],[0.939,0.317],[0,0],[0.136,-0.428],[0,0],[-0.423,-0.143],[0,0],[0.941,-0.301],[0,0],[-0.138,-0.428],[0,0],[-0.423,0.143],[0,0],[0.579,-0.825],[0,0],[-0.36,-0.27],[0,0],[-0.262,0.365],[0,0],[-0.036,-0.983],[0,0],[-0.446,0],[0,0],[0,0.46],[0,0],[-0.573,-0.809],[0,0],[-0.362,0.27],[0,0],[0.262,0.381],[0,0],[-0.942,-0.317],[0,0],[-0.138,0.428],[0,0],[0.423,0.143]],"o":[[0,0],[-0.939,-0.301],[0,0],[0.423,-0.143],[0,0],[-0.138,-0.428],[0,0],[-0.941,0.317],[0,0],[0.262,-0.381],[0,0],[-0.36,-0.27],[0,0],[-0.573,0.809],[0,0],[0,-0.46],[0,0],[-0.446,0],[0,0],[-0.036,0.983],[0,0],[-0.262,-0.365],[0,0],[-0.36,0.27],[0,0],[0.58,0.825],[0,0],[-0.423,-0.143],[0,0],[-0.136,0.428],[0,0],[0.941,0.301],[0,0],[-0.423,0.143],[0,0],[0.136,0.428],[0,0],[0.939,-0.317],[0,0],[-0.262,0.381],[0,0],[0.36,0.27],[0,0],[0.574,-0.809],[0,0],[0,0.46],[0,0],[0.446,0],[0,0],[0.035,-0.983],[0,0],[0.262,0.365],[0,0],[0.358,-0.27],[0,0],[-0.582,-0.825],[0,0],[0.423,0.143],[0,0],[0.136,-0.428],[0,0]],"v":[[14.508,3.093],[8.175,0.983],[8.175,-0.999],[14.508,-3.093],[15.025,-4.124],[14.533,-5.678],[13.517,-6.201],[7.185,-4.108],[6.045,-5.71],[9.957,-11.198],[9.78,-12.355],[8.489,-13.307],[7.361,-13.133],[3.448,-7.629],[1.605,-8.2],[1.605,-15.036],[0.798,-15.86],[-0.801,-15.86],[-1.606,-15.036],[-1.606,-8.2],[-3.449,-7.629],[-7.364,-13.133],[-8.49,-13.307],[-9.781,-12.355],[-9.96,-11.198],[-6.046,-5.71],[-7.186,-4.108],[-13.519,-6.201],[-14.534,-5.678],[-15.028,-4.124],[-14.509,-3.093],[-8.177,-0.983],[-8.177,0.983],[-14.509,3.093],[-15.028,4.124],[-14.534,5.678],[-13.519,6.201],[-7.186,4.108],[-6.044,5.71],[-9.959,11.198],[-9.779,12.355],[-8.488,13.307],[-7.362,13.133],[-3.449,7.629],[-1.605,8.2],[-1.605,15.036],[-0.799,15.86],[0.8,15.86],[1.607,15.036],[1.607,8.2],[3.45,7.629],[7.363,13.133],[8.49,13.307],[9.781,12.355],[9.959,11.198],[6.046,5.71],[7.188,4.108],[13.52,6.201],[14.536,5.678],[15.028,4.124],[14.511,3.093]],"c":true},"ix":2},"nm":"Path 1","mn":"ADBE Vector Shape - Group","hd":false},{"ty":"fl","c":{"a":0,"k":[1,0.713725507259,0.517647087574,1],"ix":4},"o":{"a":0,"k":100,"ix":5},"r":1,"bm":0,"nm":"Fill 1","mn":"ADBE Vector Graphic - Fill","hd":false},{"ty":"tr","p":{"a":0,"k":[0,0],"ix":2},"a":{"a":0,"k":[0,0],"ix":1},"s":{"a":0,"k":[100,100],"ix":3},"r":{"a":0,"k":0,"ix":6},"o":{"a":0,"k":100,"ix":7},"sk":{"a":0,"k":0,"ix":4},"sa":{"a":0,"k":0,"ix":5},"nm":"Transform"}],"nm":"Group 1","np":2,"cix":2,"bm":0,"ix":1,"mn":"ADBE Vector Group","hd":false}],"ip":4.00000016292334,"op":150.000006109625,"st":0,"bm":0},{"ddd":0,"ind":7,"ty":4,"nm":"Sparks6","sr":1,"ks":{"o":{"a":0,"k":100,"ix":11},"r":{"a":0,"k":0,"ix":10},"p":{"a":0,"k":[180.29,144.17,0],"ix":2},"a":{"a":0,"k":[0,0,0],"ix":1},"s":{"a":0,"k":[62,62,100],"ix":6}},"ao":0,"shapes":[{"ty":"gr","it":[{"ty":"rc","d":1,"s":{"a":1,"k":[{"i":{"x":[0.667,0.667],"y":[1,1]},"o":{"x":[0.333,0.333],"y":[0,0]},"t":0,"s":[0,0]},{"i":{"x":[0.29,0.29],"y":[1,1]},"o":{"x":[0.333,0.333],"y":[0,0]},"t":6.993,"s":[10,20]},{"t":20.1225008196062,"s":[0,0]}],"ix":2},"p":{"a":1,"k":[{"i":{"x":0.29,"y":1},"o":{"x":0.333,"y":0},"t":0,"s":[0,100],"to":[0,25],"ti":[0,-25]},{"t":20.1225008196062,"s":[0,250]}],"ix":3},"r":{"a":0,"k":30,"ix":4},"nm":"Rectangle Path 1","mn":"ADBE Vector Shape - Rect","hd":false},{"ty":"fl","c":{"a":0,"k":[1,0.807843197093,0,1],"ix":4},"o":{"a":0,"k":100,"ix":5},"r":1,"bm":0,"nm":"Fill 1","mn":"ADBE Vector Graphic - Fill","hd":false},{"ty":"rp","c":{"a":1,"k":[{"i":{"x":[0.667],"y":[1]},"o":{"x":[0.333],"y":[0]},"t":0,"s":[0]},{"t":12.9875005289917,"s":[20]}],"ix":1},"o":{"a":1,"k":[{"i":{"x":[0.667],"y":[1]},"o":{"x":[0.333],"y":[0]},"t":0,"s":[0]},{"t":12.9875005289917,"s":[19]}],"ix":2},"m":1,"ix":3,"tr":{"ty":"tr","p":{"a":0,"k":[0,0],"ix":2},"a":{"a":0,"k":[0,100],"ix":1},"s":{"a":0,"k":[100,100],"ix":3},"r":{"a":0,"k":18,"ix":4},"so":{"a":0,"k":100,"ix":5},"eo":{"a":0,"k":100,"ix":6},"nm":"Transform"},"nm":"Repeater 1","mn":"ADBE Vector Filter - Repeater","hd":false},{"ty":"tr","p":{"a":0,"k":[0,0],"ix":2},"a":{"a":0,"k":[0,100],"ix":1},"s":{"a":0,"k":[100,100],"ix":3},"r":{"a":0,"k":0,"ix":6},"o":{"a":0,"k":100,"ix":7},"sk":{"a":0,"k":0,"ix":4},"sa":{"a":0,"k":0,"ix":5},"nm":"Transform"}],"nm":"Rectangle 2","np":3,"cix":2,"bm":0,"ix":2,"mn":"ADBE Vector Group","hd":false}],"ip":0,"op":62.9370025634766,"st":0,"bm":0}],"markers":[]}